{
	"index": 1,
	"background": "res://resources/environment/backgrounds/background.png",
	"triggers": [
		{
			"action": "start_dialogue",
			"position": 0,
			"args": {
				"dialogue": "lampy"
			}
		},
		{
			"action": "start_battle",
			"position": 400,
			"args": {
				"encounters": [["Thornpawn"]],
				"post_dialogue": "bedroom_defeated_1"
			}
		},
		{
			"action": "start_battle",
			"position": 800,
			"args": {
				"encounters": [["Thornpawn"]],
				"post_dialogue": "bedroom_defeated_2"
			}
		},
		{
			"action": "start_battle",
			"position": 1200,
			"args": {
				"encounters": [["Thornpawn"]],
				"post_dialogue": "bedroom_defeated_3"
			}
		},
		{
			"action": "next_act",
			"position": 1600,
			"args": {}
		}
	]
}
